gcloud_storage_emulator/__init__.py
gcloud_storage_emulator/__main__.py
gcloud_storage_emulator/exceptions.py
gcloud_storage_emulator/server.py
gcloud_storage_emulator/settings.py
gcloud_storage_emulator/storage.py
gcloud_storage_emulator/handlers/__init__.py
gcloud_storage_emulator/handlers/buckets.py
gcloud_storage_emulator/handlers/objects.py
gcloud_storage_emulator/tests/__init__.py
gcloud_storage_emulator/tests/test_server.py
gcloud_storage_emulator/tests/test_storage.py
gcloud_storage_emulator-0.5.0.data/scripts/gcloud-storage-emulator
gcloud_storage_emulator-0.5.0.data/scripts/gcloud-storage-emulator.py
gcloud_storage_emulator-0.5.0.dist-info/LICENCE.md
gcloud_storage_emulator-0.5.0.dist-info/METADATA
gcloud_storage_emulator-0.5.0.dist-info/WHEEL
gcloud_storage_emulator-0.5.0.dist-info/top_level.txt
gcloud_storage_emulator-0.5.0.dist-info/RECORD
