Metadata-Version: 2.1
Name: gcloud-storage-emulator
Version: 0.5.0
Summary: A stub emulator for the Google Cloud Storage API
Home-page: https://gitlab.com/potato-oss/google-cloud/gcloud-storage-emulator
Author: Potato London Ltd.
Author-email: mail@p.ota.to
License: UNKNOWN
Keywords: Google Cloud Storage,Google App Engine,GAE,GCS
Platform: UNKNOWN
Classifier: Development Status :: 3 - Alpha
Classifier: Intended Audience :: Developers
Classifier: License :: OSI Approved :: BSD License
Classifier: Operating System :: OS Independent
Classifier: Programming Language :: Python
Requires-Python: >=3.6
License-File: LICENCE.md
Requires-Dist: fs
Requires-Dist: google-cloud-storage
Requires-Dist: requests
